IPYNBrendererA/__init__.py
IPYNBrendererA/site.py
IPYNBrendererA/youtubeRender.py
IPYNBrendererA/exception/__init__.py
IPYNBrendererA/logger/__init__.py
wasim_utils_packed-0.0.2.dist-info/LICENSE
wasim_utils_packed-0.0.2.dist-info/METADATA
wasim_utils_packed-0.0.2.dist-info/WHEEL
wasim_utils_packed-0.0.2.dist-info/top_level.txt
wasim_utils_packed-0.0.2.dist-info/RECORD
